ovp_docker_utils/__init__.py
ovp_docker_utils/__version__.py
ovp_docker_utils/defaults.py
ovp_docker_utils/docker_compose_instance.py
ovp_docker_utils/oem_logging.py
ovp_docker_utils/ovp_docker_utils.py
ovp_docker_utils/ssh_file_utils.py
ovp_docker_utils/ssh_key_gen.py
ovp_docker_utils-1.0.20.dist-info/LICENSE
ovp_docker_utils-1.0.20.dist-info/METADATA
ovp_docker_utils-1.0.20.dist-info/WHEEL
ovp_docker_utils-1.0.20.dist-info/entry_points.txt
ovp_docker_utils-1.0.20.dist-info/top_level.txt
ovp_docker_utils-1.0.20.dist-info/RECORD
