Metadata-Version: 2.1
Name: ovp_docker_utils
Version: 1.0.20
Summary: O3R docker deployment utilities
Author: ifm gmbh
Author-email: support.efector.object.ident@ifm.com
License: Apache 2.0
License-File: LICENSE
Requires-Dist: pyyaml
Requires-Dist: scp
Requires-Dist: ifm3dpy
Requires-Dist: pydantic
Requires-Dist: semver
